ode2tn/__init__.py
ode2tn/transform.py
ode2tn-1.1.0.dist-info/licenses/LICENSE
ode2tn-1.1.0.dist-info/METADATA
ode2tn-1.1.0.dist-info/WHEEL
ode2tn-1.1.0.dist-info/top_level.txt
ode2tn-1.1.0.dist-info/RECORD
