Metadata-Version: 2.4
Name: ode2tn
Version: 1.1.0
Summary: A Python package to turn arbitrary polynomial ODEs into a transcriptional network simulating it.
Author-email: Dave Doty <doty@ucdavis.edu>
License-Expression: MIT
Project-URL: Homepage, https://github.com/UC-Davis-molecular-computing/ode2tn
Project-URL: Issues, https://github.com/UC-Davis-molecular-computing/ode2tn/issues
Requires-Python: >=3.10
License-File: LICENSE
Requires-Dist: gpac
Requires-Dist: scipy>=1.15
Requires-Dist: sympy>=1.13
Dynamic: license-file
